README.rst
diffbot.py
setup.cfg
setup.py
diffbot.egg-info/PKG-INFO
diffbot.egg-info/SOURCES.txt
diffbot.egg-info/dependency_links.txt
diffbot.egg-info/entry_points.txt
diffbot.egg-info/top_level.txt
diffbot.egg-info/zip-safe